{
  "CompanyId": 1,
  "MerchantId": 1,
  "StoreId": 1,
  "TerminalId": 1,

  "TerminalConfiguration": {
    "TerminalIdentification": "0x0000000000000001",
    "MerchantIdentifier": "0x000000000000000000000000000001",
    "MerchantCategoryCode": "0x15DF",
    "MerchantNameAndLocation": "0x506C6179204C4C432E2044616C6C61732C205458",
    "AcquirerIdentifier": "0x000000000001",
    "InterfaceDeviceSerialNumber": "0x0000000000000001",
    "TerminalType": "0x15",
    "TerminalCapabilities": "0x80A8C8",
    "AdditionalTerminalCapabilities": "0x00",
    "TerminalCountryCode": "0x0348",
    "LanguagePreference": "0x454E",
    "TransactionCurrencyCode": "0x0348",
    "TransactionCurrencyExponent": "0x02",
    "TransactionReferenceCurrencyCode": "0x0348",
    "TransactionReferenceCurrencyExponent": "0x02",
    "TerminalFloorLimit": "0x00",
    "TerminalRiskManagementData": "0x00",
    "DataStorageRequestedOperatorId": "0x01",
    "BiasedRandomSelectionProbability": "0x00",
    "BiasedRandomSelectionTargetProbability": "0x00",
    "ThresholdValueForBiasedRandomSelection": "0x00",
    "MaxNumberOfTornTransactionLogRecords": "0x01",
    "MaxLifetimeOfTornTransactionLogRecords": "0x012C",
    "SequenceConfiguration": {
      "Threshold": 999999,
      "InitializationValue": 1
    }
  },
  "TransactionProfiles": [
    {
      "KernelId": 2,
      "ApplicationId": "A000000004",
      "TransactionType": 0,
      "ApplicationPriorityIndicator": 1,
      "ReaderContactlessTransactionLimitWhenCvmIsNotOnDevice": 0,
      "ReaderContactlessTransactionLimitWhenCvmIsOnDevice": 0,
      "ReaderContactlessFloorLimit": 0,
      "ReaderCvmRequiredLimit": 0,
      "KernelConfiguration": 112,
      "TerminalTransactionQualifiers": 645939200,
      "IsStatusCheckSupported": true,
      "IsZeroAmountAllowed": false,
      "IsZeroAmountAllowedForOffline": false,
      "IsExtendedSelectionSupported": false
    },
    {
      "KernelId": 2,
      "ApplicationId": "A000000004",
      "TransactionType": 9,
      "ApplicationPriorityIndicator": 1,
      "ReaderContactlessTransactionLimitWhenCvmIsNotOnDevice": 0,
      "ReaderContactlessTransactionLimitWhenCvmIsOnDevice": 0,
      "ReaderContactlessFloorLimit": 0,
      "ReaderCvmRequiredLimit": 0,
      "KernelConfiguration": 112,
      "TerminalTransactionQualifiers": 645939200,
      "IsStatusCheckSupported": true,
      "IsZeroAmountAllowed": false,
      "IsZeroAmountAllowedForOffline": false,
      "IsExtendedSelectionSupported": false
    },

    {
      "KernelId": 2,
      "ApplicationId": "A000000004",
      "TransactionType": 32,
      "ApplicationPriorityIndicator": 1,
      "ReaderContactlessTransactionLimitWhenCvmIsNotOnDevice": 0,
      "ReaderContactlessTransactionLimitWhenCvmIsOnDevice": 0,
      "ReaderContactlessFloorLimit": 0,
      "ReaderCvmRequiredLimit": 0,
      "KernelConfiguration": 112,
      "TerminalTransactionQualifiers": 645939200,
      "IsStatusCheckSupported": true,
      "IsZeroAmountAllowed": false,
      "IsZeroAmountAllowedForOffline": false,
      "IsExtendedSelectionSupported": false
    }

  ],
  "KernelPersistentConfigurations": [
    {

      "KernelId": 2,
      "TagLengthValues": [
        {
          "Name": "ApplicationVersionNumberReader",
          "Tag": "0x9F09",
          "Value": "0x02"
        },
        {
          "Name": "CardDataInputCapability",
          "Tag": "0xDF8117",
          "Value": "0x00"
        },
        {
          "Name": "CvmCapabilityCvmRequired",
          "Tag": "0xDF8118",
          "Value": "0x00"
        },
        {
          "Name": "CvmCapabilityNoCvmRequired",
          "Tag": "0xDF8119",
          "Value": "0x00"
        },
        {
          "Name": "UnpredictableNumberDataObjectList",
          "Tag": "0x9F69",
          "Value": "0x9F6A04"
        },
        {
          "Name": "HoldTimeValue",
          "Tag": "0xDF8130",
          "Value": "0x0B"
        },
        {
          "Name": "MagstripeApplicationVersionNumberReader",
          "Tag": "0x9F6D",
          "Value": "0x01"
        },
        {
          "Name": "MagstripeCvmCapabilityCvmRequired",
          "Tag": "0xDF811E",
          "Value": "0xF0"
        },
        {
          "Name": "MagstripeCvmCapabilityNoCvmRequired",
          "Tag": "0xDF812C",
          "Value": "0xF0"
        },
        {
          "Name": "MaxLifetimeOfTornTransactionLogRecords",
          "Tag": "0xDF811C",
          "Value": "0x012C"
        },
        {
          "Name": "MaxNumberOfTornTransactionLogRecords",
          "Tag": "0xDF811D",
          "Value": "0x00"
        },
        {
          "Name": "MessageHoldTime",
          "Tag": "0xDF812D",
          "Value": "0x13"
        },
        {
          "Name": "CvmCapabilityNoCvmRequired",
          "Tag": "0xDF8119",
          "Value": "0x00"
        },
        {
          "Name": "MaximumRelayResistanceGracePeriod",
          "Tag": "0xDF8133",
          "Value": "0x32"
        },
        {
          "Name": "MinimumRelayResistanceGracePeriod",
          "Tag": "0xDF8132",
          "Value": "0x14"
        },
        {
          "Name": "ReaderContactlessFloorLimit",
          "Tag": "0xDF8123",
          "Value": "0x00"
        },
        {
          "Name": "ReaderContactlessTransactionLimitWhenCvmIsNotOnDevice",
          "Tag": "0xDF8124",
          "Value": "0x00"
        },
        {
          "Name": "ReaderContactlessTransactionLimitWhenCvmIsOnDevice",
          "Tag": "0xDF8125",
          "Value": "0x00"
        },
        {
          "Name": "ReaderCvmRequiredLimit",
          "Tag": "0xDF8126",
          "Value": "0x00"
        },
        {
          "Name": "RelayResistanceAccuracyThreshold",
          "Tag": "0xDF8136",
          "Value": "0x012C"
        },
        {
          "Name": "RelayResistanceTransmissionTimeMismatchThreshold",
          "Tag": "0xDF8137",
          "Value": "0x32"
        },
        {
          "Name": "TerminalActionCodeDefault",
          "Tag": "0xDF8120",
          "Value": "0x840000000C"
        },
        {
          "Name": "TerminalActionCodeDenial",
          "Tag": "0xDF8121",
          "Value": "0x840000000C"
        },
        {
          "Name": "TerminalActionCodeOnline",
          "Tag": "0xDF8122",
          "Value": "0x840000000C"
        },
        {
          "Name": "TerminalExpectedTransmissionTimeForRelayResistanceCapdu",
          "Tag": "0xDF8134",
          "Value": "0x12"
        },
        {
          "Name": "TimeoutValue",
          "Tag": "0xDF8127",
          "Value": "0x01F4"
        },
        {
          "Name": "PhoneMessageTable",
          "Tag": "0xDF8131",
          "Value": "0x00080000080020000004000004002000000100000100200000020000020020000000000000000700"
        }
      ]
    }
  ],
  "DisplayConfiguration": {
    "MessageHoldTime": "0x64",
    "DisplayMessageSets": [
      {
        "LanguageCode": "EN",
        "CountryCode": "0x0348",
        "DisplayMessages": [
          {
            "MessageIdentifier": "03",
            "Message": "Approved"
          },
          {
            "MessageIdentifier": "07",
            "Message": "Not Authorized"
          },
          {
            "MessageIdentifier": "09",
            "Message": "Please enter your PIN"
          },
          {
            "MessageIdentifier": "0F",
            "Message": "Processing Error"
          },
          {
            "MessageIdentifier": "10",
            "Message": "Please remove card"
          },
          {
            "MessageIdentifier": "14",
            "Message": "Welcome"
          },
          {
            "MessageIdentifier": "15",
            "Message": "Present card"
          },
          {
            "MessageIdentifier": "16",
            "Message": "Processing"
          },
          {
            "MessageIdentifier": "17",
            "Message": "Card read OK Please remove card"
          },
          {
            "MessageIdentifier": "18",
            "Message": "Please insert or swipe card"
          },
          {
            "MessageIdentifier": "19",
            "Message": "Please present one card only"
          },
          {
            "MessageIdentifier": "1A",
            "Message": "Approved Please sign"
          },
          {
            "MessageIdentifier": "1B",
            "Message": "Authorizing Please wait"
          },
          {
            "MessageIdentifier": "1C",
            "Message": "Insert, swipe or try another card"
          },
          {
            "MessageIdentifier": "1D",
            "Message": "Please insert card"
          },
          {
            "MessageIdentifier": "1E",
            "Message": ""
          },
          {
            "MessageIdentifier": "20",
            "Message": "See Phone for instructions"
          },
          {
            "MessageIdentifier": "21",
            "Message": "Present card again"
          },
          {
            "MessageIdentifier": "07",
            "Message": "Not Authorized"
          },
          {
            "MessageIdentifier": "07",
            "Message": "Not Authorized"
          },
          {
            "MessageIdentifier": "07",
            "Message": "Not Authorized"
          },
          {
            "MessageIdentifier": "07",
            "Message": "Not Authorized"
          },
          {
            "MessageIdentifier": "07",
            "Message": "Not Authorized"
          },
          {
            "MessageIdentifier": "07",
            "Message": "Not Authorized"
          },
          {
            "MessageIdentifier": "07",
            "Message": "Not Authorized"
          },
          {
            "MessageIdentifier": "07",
            "Message": "Not Authorized"
          },
          {
            "MessageIdentifier": "07",
            "Message": "Not Authorized"
          },
          {
            "MessageIdentifier": "07",
            "Message": "Not Authorized"
          },
          {
            "MessageIdentifier": "07",
            "Message": "Not Authorized"
          },
          {
            "MessageIdentifier": "07",
            "Message": "Not Authorized"
          },
          {
            "MessageIdentifier": "07",
            "Message": "Not Authorized"
          },
          {
            "MessageIdentifier": "07",
            "Message": "Not Authorized"
          },
          {
            "MessageIdentifier": "07",
            "Message": "Not Authorized"
          },
          {
            "MessageIdentifier": "07",
            "Message": "Not Authorized"
          }
        ]
      }
    ]
  },
  "ProximityCouplingDeviceConfiguration": {
    "TimeoutValue": 500
  },
  "CertificateAuthorityConfiguration": {
    "Certificates": [
      {
        "RegisteredApplicationProviderIndicator": "0xA000000025",
        "PublicKeyIndex": "0x67",
        "HashAlgorithmIndicator": 1,
        "PublicKeyAlgorithmIndicator": 1,
        "ActivationDate": "0820",
        "ExpirationDate": "1222",
        "Exponent": 3,
        "Modulus": "0xC687ADCCF3D57D3360B174E471EDA693AA555DFDC6C8CD394C74BA25CCDF8EABFD1F1CEADFBE2280C9E81F7A058998DC22B7F22576FE84713D0BDD3D34CFCD12FCD0D26901BA74103D075C664DABCCAF57BF789494051C5EC303A2E1D784306D3DB3EB665CD360A558F40B7C05C919B2F0282FE1ED9BF6261AA814648FBC263B14214491DE426D242D65CD1FFF0FBE4D4DAFF5CFACB2ADC7131C9B147EE791956551076270696B75FD97373F1FD7804F",
        "Checksum": "0x52A2907300C8445BF54B970C894691FEADF2D28E",
        "IsRevoked": false,
        "CertificateSerialNumber": "0x000001"
      },
      {
        "RegisteredApplicationProviderIndicator": "0xA000000025",
        "PublicKeyIndex": "0x0E",
        "HashAlgorithmIndicator": 1,
        "PublicKeyAlgorithmIndicator": 1,
        "ActivationDate": "0820",
        "ExpirationDate": "1213",
        "Exponent": 3,
        "Modulus": "0xAA94A8C6DAD24F9BA56A27C09B01020819568B81A026BE9FD0A3416CA9A71166ED5084ED91CED47DD457DB7E6CBCD53E560BC5DF48ABC380993B6D549F5196CFA77DFB20A0296188E969A2772E8C4141665F8BB2516BA2C7B5FC91F8DA04E8D512EB0F6411516FB86FC021CE7E969DA94D33937909A53A57F907C40C22009DA7532CB3BE509AE173B39AD6A01BA5BB85",
        "Checksum": "0xA7266ABAE64B42A3668851191D49856E17F8FBCD",
        "IsRevoked": false,
        "CertificateSerialNumber": "0x000001"
      },
      {
        "RegisteredApplicationProviderIndicator": "0xA000000025",
        "PublicKeyIndex": "0x0F",
        "HashAlgorithmIndicator": 1,
        "PublicKeyAlgorithmIndicator": 1,
        "ActivationDate": "0820",
        "ExpirationDate": "1222",
        "Exponent": 3,
        "Modulus": "0xC8D5AC27A5E1FB89978C7C6479AF993AB3800EB243996FBB2AE26B67B23AC482C4B746005A51AFA7D2D83E894F591A2357B30F85B85627FF15DA12290F70F05766552BA11AD34B7109FA49DE29DCB0109670875A17EA95549E92347B948AA1F045756DE56B707E3863E59A6CBE99C1272EF65FB66CBB4CFF070F36029DD76218B21242645B51CA752AF37E70BE1A84FF31079DC0048E928883EC4FADD497A719385C2BBBEBC5A66AA5E5655D18034EC5",
        "Checksum": "0xA73472B3AB557493A9BC2179CC8014053B12BAB4",
        "IsRevoked": false,
        "CertificateSerialNumber": "0x000001"
      },
      {
        "RegisteredApplicationProviderIndicator": "0xA000000141",
        "PublicKeyIndex": "0x2",
        "HashAlgorithmIndicator": 1,
        "PublicKeyAlgorithmIndicator": 1,
        "ActivationDate": "0820",
        "ExpirationDate": "1209",
        "Exponent": 3,
        "Modulus": "0xAFD753699B6FC2E5CBEACBB6B147C572A57EDE98F4628B56CB5EDEC806DA6DCC8C85CB4585933046746D0DD79FDDBE7549542116BBAD2FD35F74A8C33F746FD0EC5BC6241B112B212F8C5F4A864AF403BD944C3FDA1924FD4D7CDF79074306C922513B883C24E567AFC2A641F35DFEFF9CA2825F9FA4409D65D3C95F327289D3",
        "Checksum": "0x315763F649BC0C0366F991EBCF01BAF1A833E51B",
        "IsRevoked": false,
        "CertificateSerialNumber": "0x000001"
      },
      {
        "RegisteredApplicationProviderIndicator": "0xA000000141",
        "PublicKeyIndex": "0x4",
        "HashAlgorithmIndicator": 1,
        "PublicKeyAlgorithmIndicator": 1,
        "ActivationDate": "0820",
        "ExpirationDate": "1218",
        "Exponent": 3,
        "Modulus": "0xE7EDCA9D810F3792DC4EF1A1C9F3803FD3904000AF9C3E322B7516CD41A6231A9629C0AD5A4CDF9F40750FA51D2DA9DCC1E3F5B36F032A8086C58930FDC10B2839909B19B9CA23265A62764A932C37C6566D1392F03486C626A9F6C204E1266069602DEC0F31D8A58CF394FD96939B1E14E2BE91B818C492CCD1BA63F410E5F331ED48013F1E9911632A3B3A5AE24629C544507CBEADE6B5CE2FF77C2CD4DF921D693423EA88AEA004571461FAB2932E46C06E9EA63D24A05666DFD91B57FC58959C24B9041624FDC33A33F02E109955E1F16524F324161FBDA3540C6141FBF67023C5263BF5FBC5C83B4EFAEE822655B6A9ECABFA0189A9",
        "Checksum": "0xC54ED92B168B8773E8CE7E8F4A6D6CCA9DAD40B2",
        "IsRevoked": false,
        "CertificateSerialNumber": "0x000001"
      },
      {
        "RegisteredApplicationProviderIndicator": "0xA000000141",
        "PublicKeyIndex": "0x5",
        "HashAlgorithmIndicator": 1,
        "PublicKeyAlgorithmIndicator": 1,
        "ActivationDate": "0820",
        "ExpirationDate": "1216",
        "Exponent": 3,
        "Modulus": "0xB51658FBFB57423F690E7352DA2E527EAC3723E2F0B1D8521EDB44F4122B720D045AA54C2990CBFAB3BB3AEFADAFA6CBF65F339B75B94223C2714BD2354B12289EEE8A94F75454DCDEF0AEFBF0C2C88E1A1615F6F033787DFF9EE94863C01E4A0B1992F025624871AD2C9C57234B5FD6C9B5BE97821D0EB944A321F4E5B2A8516EDB92117CB4AB0D39504A8130C4BD0D",
        "Checksum": "0x33887D29686BCBB3BE86EA9A33CA83BBC7AE1E19",
        "IsRevoked": false,
        "CertificateSerialNumber": "0x000001"
      },
      {
        "RegisteredApplicationProviderIndicator": "0xA000000384",
        "PublicKeyIndex": "0xC1",
        "HashAlgorithmIndicator": 1,
        "PublicKeyAlgorithmIndicator": 1,
        "ActivationDate": "0820",
        "ExpirationDate": "1217",
        "Exponent": 3,
        "Modulus": "0xAD6E00E5882CEEF578AFB002980FBD901089100B921200D6442C176D93DA5C9399B8427CBE19C1B2E638F5FC78875C82BE7CE590160D0E8A04242374E5C4B5F307E7412CA8FB2E84BB4F421D6B4C2E08255B2577F55E0667673BD7D7A3D74E083DC19B597A76531135A7C3B1DB93534045E1D52DDB5170ACFAA688922C18764CFE59E3D0578C41A7BD60520CADC58DD9",
        "Checksum": "0xBF0821B417742A41F1F1AD54B8BA564EA376DD3D",
        "IsRevoked": false,
        "CertificateSerialNumber": "0x000001"
      },
      {
        "RegisteredApplicationProviderIndicator": "0xA000000384",
        "PublicKeyIndex": "0xC2",
        "HashAlgorithmIndicator": 1,
        "PublicKeyAlgorithmIndicator": 1,
        "ActivationDate": "0820",
        "ExpirationDate": "1221",
        "Exponent": 3,
        "Modulus": "0x8BFD70FC05456718B7002F1B889040780089D95969F3160A3999B4E056D2CEFC007D3033B02868670C9EFE48624096C2FD0FA7FDAFDCBB4A63A4CD7106A97BDD8CE3F71F2168AFCB4230F2C33492467A6C182B4BFA76EE605B2FEC4B4519B5A92767DF23805EC8708980E18CB089C065D036AD57D196E88AC1552148FC3B62B771B6B144D28DF5AEE74FC31521B6968909A463EA0184261DD751278A10B7C74668520B253B6A860E54065D2B5677A753",
        "Checksum": "0xC79339D404DEEC1D8532A64410D3CB786BA16124",
        "IsRevoked": false,
        "CertificateSerialNumber": "0x000001"
      },
      {
        "RegisteredApplicationProviderIndicator": "0xA000000384",
        "PublicKeyIndex": "0xC3",
        "HashAlgorithmIndicator": 1,
        "PublicKeyAlgorithmIndicator": 1,
        "ActivationDate": "0820",
        "ExpirationDate": "1221",
        "Exponent": 3,
        "Modulus": "0xA1A62B6A0393DE4EF4D9D53684C14EAED4A881A26EE64DBD4550EB3581E003281A4117F7BF9E5648FD5E3882BC4AB46B0A5F48CDF5C2D56C7D14A4CD69D337800050C0994974237628EF8D751E1FABBAAD73ED70F60486930B55A5F3C4AEBB2BB1ADAAAE3A374D02F19420BD528AB19C9D09FC41BB8140C40443AE2C5A24593C216E9604BE0DC69BBB1D1F98CA76212D5D1B59DBB90739145C5F98C7DEFECBE91DA4C59FB40F159A260A0B058861A25D0B88D0B3FFD87CEE52DD28C7B1FFE50A49B66116615DC45696B4A61E563B3CDD36E3F2ADCFFB50DBC3E8280412769D00662917096893B1C319E8133A043DDF05AE82A55FAEFEC1DF",
        "Checksum": "0x6DCF1357576D142C1F217CA5C8727EE8926F5FD1",
        "IsRevoked": false,
        "CertificateSerialNumber": "0x000001"
      },
      {
        "RegisteredApplicationProviderIndicator": "0xA000000333",
        "PublicKeyIndex": "0x1",
        "HashAlgorithmIndicator": 1,
        "PublicKeyAlgorithmIndicator": 1,
        "ActivationDate": "0820",
        "ExpirationDate": "1209",
        "Exponent": 3,
        "Modulus": "0xBBE9066D2517511D239C7BFA77884144AE20C7372F515147E8CE6537C54C0A6A4D45F8CA4D290870CDA59F1344EF71D17D3F35D92F3F06778D0D511EC2A7DC4FFEADF4FB1253CE37A7B2B5A3741227BEF72524DA7A2B7B1CB426BEE27BC513B0CB11AB99BC1BC61DF5AC6CC4D831D0848788CD74F6D543AD37C5A2B4C5D5A93B",
        "Checksum": "0xE881E390675D44C2DD81234DCE29C3F5AB2297A0",
        "IsRevoked": false,
        "CertificateSerialNumber": "0x000001"
      },
      {
        "RegisteredApplicationProviderIndicator": "0xA000000333",
        "PublicKeyIndex": "0x2",
        "HashAlgorithmIndicator": 1,
        "PublicKeyAlgorithmIndicator": 1,
        "ActivationDate": "0820",
        "ExpirationDate": "1221",
        "Exponent": 3,
        "Modulus": "0xA3767ABD1B6AA69D7F3FBF28C092DE9ED1E658BA5F0909AF7A1CCD907373B7210FDEB16287BA8E78E1529F443976FD27F991EC67D95E5F4E96B127CAB2396A94D6E45CDA44CA4C4867570D6B07542F8D4BF9FF97975DB9891515E66F525D2B3CBEB6D662BFB6C3F338E93B02142BFC44173A3764C56AADD202075B26DC2F9F7D7AE74BD7D00FD05EE430032663D27A57",
        "Checksum": "0x03BB335A8549A03B87AB089D006F60852E4B8060",
        "IsRevoked": false,
        "CertificateSerialNumber": "0x000001"
      },
      {
        "RegisteredApplicationProviderIndicator": "0xA000000333",
        "PublicKeyIndex": "0x3",
        "HashAlgorithmIndicator": 1,
        "PublicKeyAlgorithmIndicator": 1,
        "ActivationDate": "0820",
        "ExpirationDate": "1224",
        "Exponent": 3,
        "Modulus": "0xB0627DEE87864F9C18C13B9A1F025448BF13C58380C91F4CEBA9F9BCB214FF8414E9B59D6ABA10F941C7331768F47B2127907D857FA39AAF8CE02045DD01619D689EE731C551159BE7EB2D51A372FF56B556E5CB2FDE36E23073A44CA215D6C26CA68847B388E39520E0026E62294B557D6470440CA0AEFC9438C923AEC9B2098D6D3A1AF5E8B1DE36F4B53040109D89B77CAFAF70C26C601ABDF59EEC0FDC8A99089140CD2E817E335175B03B7AA33D",
        "Checksum": "0x87F0CD7C0E86F38F89A66F8C47071A8B88586F26",
        "IsRevoked": false,
        "CertificateSerialNumber": "0x000001"
      },
      {
        "RegisteredApplicationProviderIndicator": "0xA000000333",
        "PublicKeyIndex": "0x4",
        "HashAlgorithmIndicator": 1,
        "PublicKeyAlgorithmIndicator": 1,
        "ActivationDate": "0820",
        "ExpirationDate": "1224",
        "Exponent": 3,
        "Modulus": "0xBC853E6B5365E89E7EE9317C94B02D0ABB0DBD91C05A224A2554AA29ED9FCB9D86EB9CCBB322A57811F86188AAC7351C72BD9EF196C5A01ACEF7A4EB0D2AD63D9E6AC2E7836547CB1595C68BCBAFD0F6728760F3A7CA7B97301B7E0220184EFC4F653008D93CE098C0D93B45201096D1ADFF4CF1F9FC02AF759DA27CD6DFD6D789B099F16F378B6100334E63F3D35F3251A5EC78693731F5233519CDB380F5AB8C0F02728E91D469ABD0EAE0D93B1CC66CE127B29C7D77441A49D09FCA5D6D9762FC74C31BB506C8BAE3C79AD6C2578775B95956B5370D1D0519E37906B384736233251E8F09AD79DFBE2C6ABFADAC8E4D8624318C27DAF1",
        "Checksum": "0xF527081CF371DD7E1FD4FA414A665036E0F5E6E5",
        "IsRevoked": false,
        "CertificateSerialNumber": "0x000001"
      },
      {
        "RegisteredApplicationProviderIndicator": "0xA000000333",
        "PublicKeyIndex": "0x8",
        "HashAlgorithmIndicator": 1,
        "PublicKeyAlgorithmIndicator": 1,
        "ActivationDate": "0820",
        "ExpirationDate": "1230",
        "Exponent": 3,
        "Modulus": "0xB61645EDFD5498FB246444037A0FA18C0F101EBD8EFA54573CE6E6A7FBF63ED21D66340852B0211CF5EEF6A1CD989F66AF21A8EB19DBD8DBC3706D135363A0D683D046304F5A836BC1BC632821AFE7A2F75DA3C50AC74C545A754562204137169663CFCC0B06E67E2109EBA41BC67FF20CC8AC80D7B6EE1A95465B3B2657533EA56D92D539E5064360EA4850FED2D1BF",
        "Checksum": "0xEE23B616C95C02652AD18860E48787C079E8E85A",
        "IsRevoked": false,
        "CertificateSerialNumber": "0x000001"
      },
      {
        "RegisteredApplicationProviderIndicator": "0xA000000333",
        "PublicKeyIndex": "0x9",
        "HashAlgorithmIndicator": 1,
        "PublicKeyAlgorithmIndicator": 1,
        "ActivationDate": "0820",
        "ExpirationDate": "1230",
        "Exponent": 3,
        "Modulus": "0xEB374DFC5A96B71D2863875EDA2EAFB96B1B439D3ECE0B1826A2672EEEFA7990286776F8BD989A15141A75C384DFC14FEF9243AAB32707659BE9E4797A247C2F0B6D99372F384AF62FE23BC54BCDC57A9ACD1D5585C303F201EF4E8B806AFB809DB1A3DB1CD112AC884F164A67B99C7D6E5A8A6DF1D3CAE6D7ED3D5BE725B2DE4ADE23FA679BF4EB15A93D8A6E29C7FFA1A70DE2E54F593D908A3BF9EBBD760BBFDC8DB8B54497E6C5BE0E4A4DAC29E5",
        "Checksum": "0xA075306EAB0045BAF72CDD33B3B678779DE1F527",
        "IsRevoked": false,
        "CertificateSerialNumber": "0x000001"
      },
      {
        "RegisteredApplicationProviderIndicator": "0xA000000333",
        "PublicKeyIndex": "0x0A",
        "HashAlgorithmIndicator": 1,
        "PublicKeyAlgorithmIndicator": 1,
        "ActivationDate": "0820",
        "ExpirationDate": "1230",
        "Exponent": 3,
        "Modulus": "0xB2AB1B6E9AC55A75ADFD5BBC34490E53C4C3381F34E60E7FAC21CC2B26DD34462B64A6FAE2495ED1DD383B8138BEA100FF9B7A111817E7B9869A9742B19E5C9DAC56F8B8827F11B05A08ECCF9E8D5E85B0F7CFA644EFF3E9B796688F38E006DEB21E101C01028903A06023AC5AAB8635F8E307A53AC742BDCE6A283F585F48EF",
        "Checksum": "0xC88BE6B2417C4F941C9371EA35A377158767E4E3",
        "IsRevoked": false,
        "CertificateSerialNumber": "0x000001"
      },
      {
        "RegisteredApplicationProviderIndicator": "0xA000000333",
        "PublicKeyIndex": "0x0B",
        "HashAlgorithmIndicator": 1,
        "PublicKeyAlgorithmIndicator": 1,
        "ActivationDate": "0820",
        "ExpirationDate": "1230",
        "Exponent": 3,
        "Modulus": "0xCF9FDF46B356378E9AF311B0F981B21A1F22F250FB11F55C958709E3C7241918293483289EAE688A094C02C344E2999F315A72841F489E24B1BA0056CFAB3B479D0E826452375DCDBB67E97EC2AA66F4601D774FEAEF775ACCC621BFEB65FB0053FC5F392AA5E1D4C41A4DE9FFDFDF1327C4BB874F1F63A599EE3902FE95E729FD78D4234DC7E6CF1ABABAA3F6DB29B7F05D1D901D2E76A606A8CBFFFFECBD918FA2D278BDB43B0434F5D45134BE1C2781D157D501FF43E5F1C470967CD57CE53B64D82974C8275937C5D8502A1252A8A5D6088A259B694F98648D9AF2CB0EFD9D943C69F896D49FA39702162ACB5AF29B90BADE005BC157",
        "Checksum": "0xBD331F9996A490B33C13441066A09AD3FEB5F66C",
        "IsRevoked": false,
        "CertificateSerialNumber": "0x000001"
      },
      {
        "RegisteredApplicationProviderIndicator": "0xA000000333",
        "PublicKeyIndex": "0x0C",
        "HashAlgorithmIndicator": 1,
        "PublicKeyAlgorithmIndicator": 1,
        "ActivationDate": "0820",
        "ExpirationDate": "1230",
        "Exponent": 3,
        "Modulus": "0xDED9E1BC8E749CAD749484BFB472445BC81FFAA89707648C342AA30D1BE60D5ED0F6CEABA25C683D4503CB11CAF91A39727593CF2BEEAE8032EFACC44FDF8DA31D6007139D4595E8655C7495CF46A9D593A83E3C65B2CBF2AF1EEA02D1F96951A946616B5AB21CA0BF34D12D05F6AE183508A7AC7A46913BDCE5FDC3914CA750018B130CA5BAD49AD8C02291ACA5CFFD",
        "Checksum": "0xD7DD7AAC8B67A9A3CC72F35F5D96F265E16EB3FE",
        "IsRevoked": false,
        "CertificateSerialNumber": "0x000001"
      },
      {
        "RegisteredApplicationProviderIndicator": "0xA000000065",
        "PublicKeyIndex": "0x9",
        "HashAlgorithmIndicator": 1,
        "PublicKeyAlgorithmIndicator": 1,
        "ActivationDate": "0820",
        "ExpirationDate": "1212",
        "Exponent": 3,
        "Modulus": "0xB72A8FEF5B27F2B550398FDCC256F714BAD497FF56094B7408328CB626AA6F0E6A9DF8388EB9887BC930170BCC1213E90FC070D52C8DCD0FF9E10FAD36801FE93FC998A721705091F18BC7C98241CADC15A2B9DA7FB963142C0AB640D5D0135E77EBAE95AF1B4FEFADCF9C012366BDDA0455C1564A68810D7127676D493890BD",
        "Checksum": "0x4410C6D51C2F83ADFD92528FA6E38A32DF048D0A",
        "IsRevoked": false,
        "CertificateSerialNumber": "0x000001"
      },
      {
        "RegisteredApplicationProviderIndicator": "0xA000000065",
        "PublicKeyIndex": "0x0A",
        "HashAlgorithmIndicator": 1,
        "PublicKeyAlgorithmIndicator": 1,
        "ActivationDate": "0820",
        "ExpirationDate": "1216",
        "Exponent": 3,
        "Modulus": "0x99B63464EE0B4957E4FD23BF923D12B61469B8FFF8814346B2ED6A780F8988EA9CF0433BC1E655F05EFA66D0C98098F25B659D7A25B8478A36E489760D071F54CDF7416948ED733D816349DA2AADDA227EE45936203CBF628CD033AABA5E5A6E4AE37FBACB4611B4113ED427529C636F6C3304F8ABDD6D9AD660516AE87F7F2DDF1D2FA44C164727E56BBC9BA23C0285",
        "Checksum": "0xB8A17CEDC3DFD3958D87AA7D87B6048CA557B787",
        "IsRevoked": false,
        "CertificateSerialNumber": "0x000001"
      },
      {
        "RegisteredApplicationProviderIndicator": "0xA000000065",
        "PublicKeyIndex": "0x0C",
        "HashAlgorithmIndicator": 1,
        "PublicKeyAlgorithmIndicator": 1,
        "ActivationDate": "0820",
        "ExpirationDate": "1219",
        "Exponent": 3,
        "Modulus": "0xADF05CD4C5B490B087C3467B0F3043750438848461288BFEFD6198DD576DC3AD7A7CFA07DBA128C247A8EAB30DC3A30B02FCD7F1C8167965463626FEFF8AB1AA61A4B9AEF09EE12B009842A1ABA01ADB4A2B170668781EC92B60F605FD12B2B2A6F1FE734BE510F60DC5D189E401451B62B4E06851EC20EBFF4522AACC2E9CDC89BC5D8CDE5D633CFD77220FF6BBD4A9B441473CC3C6FEFC8D13E57C3DE97E1269FA19F655215B23563ED1D1860D8681",
        "Checksum": "0xCD82812F9E844048F48ED56ED84EFB3267E870F8",
        "IsRevoked": false,
        "CertificateSerialNumber": "0x000001"
      },
      {
        "RegisteredApplicationProviderIndicator": "0xA000000065",
        "PublicKeyIndex": "0x0E",
        "HashAlgorithmIndicator": 1,
        "PublicKeyAlgorithmIndicator": 1,
        "ActivationDate": "0820",
        "ExpirationDate": "1219",
        "Exponent": 3,
        "Modulus": "0xAEED55B9EE00E1ECEB045F61D2DA9A66AB637B43FB5CDBDB22A2FBB25BE061E937E38244EE5132F530144A3F268907D8FD648863F5A96FED7E42089E93457ADC0E1BC89C58A0DB72675FBC47FEE9FF33C16ADE6D341936B06B6A6F5EF6F66A4EDD981DF75DA8399C3053F430ECA342437C23AF423A211AC9F58EAF09B0F837DE9D86C7109DB1646561AA5AF0289AF5514AC64BC2D9D36A179BB8A7971E2BFA03A9E4B847FD3D63524D43A0E8003547B94A8A75E519DF3177D0A60BC0B4BAB1EA59A2CBB4D2D62354E926E9C7D3BE4181E81BA60F8285A896D17DA8C3242481B6C405769A39D547C74ED9FF95A70A796046B5EFF36682DC29",
        "Checksum": "0xA163724B2CB923376367BBE06B09C03F136F4393",
        "IsRevoked": false,
        "CertificateSerialNumber": "0x000001"
      },
      {
        "RegisteredApplicationProviderIndicator": "0xA000000029",
        "PublicKeyIndex": "0x1",
        "HashAlgorithmIndicator": 1,
        "PublicKeyAlgorithmIndicator": 1,
        "ActivationDate": "0820",
        "ExpirationDate": "1209",
        "Exponent": 3,
        "Modulus": "0xC696034213D7D8546984579D1D0F0EA519CFF8DEFFC429354CF3A871A6F7183F1228DA5C7470C055387100CB935A712C4E2864DF5D64BA93FE7E63E71F25B1E5F5298575EBE1C63AA617706917911DC2A75AC28B251C7EF40F2365912490B939BCA2124A30A28F54402C34AECA331AB67E1E79B285DD5771B5D9FF79EA630B75",
        "Checksum": "0x4E4D5E501EA5D96EB81B9E22E745317CDF49A457",
        "IsRevoked": false,
        "CertificateSerialNumber": "0x000001"
      },
      {
        "RegisteredApplicationProviderIndicator": "0xA000000029",
        "PublicKeyIndex": "0x7",
        "HashAlgorithmIndicator": 1,
        "PublicKeyAlgorithmIndicator": 1,
        "ActivationDate": "0820",
        "ExpirationDate": "1214",
        "Exponent": 3,
        "Modulus": "0xA89F25A56FA6DA258C8CA8B40427D927B4A1EB4D7EA326BBB12F97DED70AE5E4480FC9C5E8A972177110A1CC318D06D2F8F5C4844AC5FA79A4DC470BB11ED635699C17081B90F1B984F12E92C1C529276D8AF8EC7F28492097D8CD5BECEA16FE4088F6CFAB4A1B42328A1B996F9278B0B7E3311CA5EF856C2F888474B83612A82E4E00D0CD4069A6783140433D50725F",
        "Checksum": "0x31A787E14B59F7D9263E8776E6E01E8863E1DBF1",
        "IsRevoked": false,
        "CertificateSerialNumber": "0x000001"
      },
      {
        "RegisteredApplicationProviderIndicator": "0xA000000029",
        "PublicKeyIndex": "0x8",
        "HashAlgorithmIndicator": 1,
        "PublicKeyAlgorithmIndicator": 1,
        "ActivationDate": "0820",
        "ExpirationDate": "1215",
        "Exponent": 3,
        "Modulus": "0xD9FD6ED75D51D0E30664BD157023EAA1FFA871E4DA65672B863D255E81E137A51DE4F72BCC9E44ACE12127F87E263D3AF9DD9CF35CA4A7B01E907000BA85D24954C2FCA3074825DDD4C0C8F186CB020F683E02F2DEAD3969133F06F7845166ACEB57CA0FC2603445469811D293BFEFBAFAB57631B3DD91E796BF850A25012F1AE38F05AA5C4D6D03B1DC2E568612785938BBC9B3CD3A910C1DA55A5A9218ACE0F7A21287752682F15832A678D6E1ED0B",
        "Checksum": "0xA960F58BE9B0266B6A6DADBA7C6C92724B58ADDE",
        "IsRevoked": false,
        "CertificateSerialNumber": "0x000001"
      },
      {
        "RegisteredApplicationProviderIndicator": "0xA000000029",
        "PublicKeyIndex": "0x9",
        "HashAlgorithmIndicator": 1,
        "PublicKeyAlgorithmIndicator": 1,
        "ActivationDate": "0820",
        "ExpirationDate": "1217",
        "Exponent": 3,
        "Modulus": "0x9D912248DE0A4E39C1A7DDE3F6D2588992C1A4095AFBD1824D1BA74847F2BC4926D2EFD904B4B54954CD189A54C5D1179654F8F9B0D2AB5F0357EB642FEDA95D3912C6576945FAB897E7062CAA44A4AA06B8FE6E3DBA18AF6AE3738E30429EE9BE03427C9D64F695FA8CAB4BFE376853EA34AD1D76BFCAD15908C077FFE6DC5521ECEF5D278A96E26F57359FFAEDA19434B937F1AD999DC5C41EB11935B44C18100E857F431A4A5A6BB65114F174C2D7B59FDF237D6BB1DD0916E644D709DED56481477C75D95CDD68254615F7740EC07F330AC5D67BCD75BF23D28A140826C026DBDE971A37CD3EF9B8DF644AC385010501EFC6509D7A41",
        "Checksum": "0xF0006035564254DCDDDEB79B30BD2841B76B5C0C",
        "IsRevoked": false,
        "CertificateSerialNumber": "0x000001"
      },
      {
        "RegisteredApplicationProviderIndicator": "0xA000000029",
        "PublicKeyIndex": "0x67",
        "HashAlgorithmIndicator": 1,
        "PublicKeyAlgorithmIndicator": 1,
        "ActivationDate": "0820",
        "ExpirationDate": "1222",
        "Exponent": 3,
        "Modulus": "0xC687ADCCF3D57D3360B174E471EDA693AA555DFDC6C8CD394C74BA25CCDF8EABFD1F1CEADFBE2280C9E81F7A058998DC22B7F22576FE84713D0BDD3D34CFCD12FCD0D26901BA74103D075C664DABCCAF57BF789494051C5EC303A2E1D784306D3DB3EB665CD360A558F40B7C05C919B2F0282FE1ED9BF6261AA814648FBC263B14214491DE426D242D65CD1FFF0FBE4D4DAFF5CFACB2ADC7131C9B147EE791956551076270696B75FD97373F1FD7804F",
        "Checksum": "0xA6269F409E9B7C574691B5E700E4A8FCD499762A",
        "IsRevoked": false,
        "CertificateSerialNumber": "0x000001"
      },
      {
        "RegisteredApplicationProviderIndicator": "0xA000000029",
        "PublicKeyIndex": "0x0E",
        "HashAlgorithmIndicator": 1,
        "PublicKeyAlgorithmIndicator": 1,
        "ActivationDate": "0820",
        "ExpirationDate": "1213",
        "Exponent": 3,
        "Modulus": "0xAA94A8C6DAD24F9BA56A27C09B01020819568B81A026BE9FD0A3416CA9A71166ED5084ED91CED47DD457DB7E6CBCD53E560BC5DF48ABC380993B6D549F5196CFA77DFB20A0296188E969A2772E8C4141665F8BB2516BA2C7B5FC91F8DA04E8D512EB0F6411516FB86FC021CE7E969DA94D33937909A53A57F907C40C22009DA7532CB3BE509AE173B39AD6A01BA5BB85",
        "Checksum": "0xB221AC6262279E9D56C54BC5F081B37F2724341F",
        "IsRevoked": false,
        "CertificateSerialNumber": "0x000001"
      },
      {
        "RegisteredApplicationProviderIndicator": "0xA000000029",
        "PublicKeyIndex": "0x0F",
        "HashAlgorithmIndicator": 1,
        "PublicKeyAlgorithmIndicator": 1,
        "ActivationDate": "0820",
        "ExpirationDate": "1222",
        "Exponent": 3,
        "Modulus": "0xC8D5AC27A5E1FB89978C7C6479AF993AB3800EB243996FBB2AE26B67B23AC482C4B746005A51AFA7D2D83E894F591A2357B30F85B85627FF15DA12290F70F05766552BA11AD34B7109FA49DE29DCB0109670875A17EA95549E92347B948AA1F045756DE56B707E3863E59A6CBE99C1272EF65FB66CBB4CFF070F36029DD76218B21242645B51CA752AF37E70BE1A84FF31079DC0048E928883EC4FADD497A719385C2BBBEBC5A66AA5E5655D18034EC5",
        "Checksum": "0x8D4D7F8DBD7182C711ADA8A044EE27FE1A055043",
        "IsRevoked": false,
        "CertificateSerialNumber": "0x000001"
      },
      {
        "RegisteredApplicationProviderIndicator": "0xA000000004",
        "PublicKeyIndex": "0x0",
        "HashAlgorithmIndicator": 1,
        "PublicKeyAlgorithmIndicator": 1,
        "ActivationDate": "0820",
        "ExpirationDate": "1209",
        "Exponent": 3,
        "Modulus": "0x9E15214212F6308ACA78B80BD986AC287516846C8D548A9ED0A42E7D997C902C3E122D1B9DC30995F4E25C75DD7EE0A0CE293B8CC02B977278EF256D761194924764942FE714FA02E4D57F282BA3B2B62C9E38EF6517823F2CA831BDDF6D363D",
        "Checksum": "0x8BB99ADDF7B560110955014505FB6B5F8308CE27",
        "IsRevoked": false,
        "CertificateSerialNumber": "0x000001"
      },
      {
        "RegisteredApplicationProviderIndicator": "0xA000000004",
        "PublicKeyIndex": "0x1",
        "HashAlgorithmIndicator": 1,
        "PublicKeyAlgorithmIndicator": 1,
        "ActivationDate": "0820",
        "ExpirationDate": "1209",
        "Exponent": 3,
        "Modulus": "0xD2010716C9FB5264D8C91A14F4F32F8981EE954F20087ED77CDC5868431728D3637C632CCF2718A4F5D92EA8AB166AB992D2DE24E9FBDC7CAB9729401E91C502D72B39F6866F5C098B1243B132AFEE65F5036E168323116338F8040834B98725",
        "Checksum": "0xEA950DD4234FEB7C900C0BE817F64DE66EEEF7C4",
        "IsRevoked": false,
        "CertificateSerialNumber": "0x000001"
      },
      {
        "RegisteredApplicationProviderIndicator": "0xA000000004",
        "PublicKeyIndex": "0x2",
        "HashAlgorithmIndicator": 1,
        "PublicKeyAlgorithmIndicator": 1,
        "ActivationDate": "0820",
        "ExpirationDate": "1209",
        "Exponent": 3,
        "Modulus": "0xCF4264E1702D34CA897D1F9B66C5D63691EACC612C8F147116BB22D0C463495BD5BA70FB153848895220B8ADEEC3E7BAB31EA22C1DC9972FA027D54265BEBF0AE3A23A8A09187F21C856607B98BDA6FC908116816C502B3E58A145254EEFEE2A3335110224028B67809DCB8058E24895",
        "Checksum": "0xAF1CC1FD1C1BC9BCA07E78DA6CBA2163F169CBB7",
        "IsRevoked": false,
        "CertificateSerialNumber": "0x000001"
      },
      {
        "RegisteredApplicationProviderIndicator": "0xA000000004",
        "PublicKeyIndex": "0x3",
        "HashAlgorithmIndicator": 1,
        "PublicKeyAlgorithmIndicator": 1,
        "ActivationDate": "0820",
        "ExpirationDate": "1209",
        "Exponent": 3,
        "Modulus": "0xC2490747FE17EB0584C88D47B1602704150ADC88C5B998BD59CE043EDEBF0FFEE3093AC7956AD3B6AD4554C6DE19A178D6DA295BE15D5220645E3C8131666FA4BE5B84FE131EA44B039307638B9E74A8C42564F892A64DF1CB15712B736E3374F1BBB6819371602D8970E97B900793C7C2A89A4A1649A59BE680574DD0B60145",
        "Checksum": "0x5ADDF21D09278661141179CBEFF272EA384B13BB",
        "IsRevoked": false,
        "CertificateSerialNumber": "0x000001"
      },
      {
        "RegisteredApplicationProviderIndicator": "0xA000000004",
        "PublicKeyIndex": "0x4",
        "HashAlgorithmIndicator": 1,
        "PublicKeyAlgorithmIndicator": 1,
        "ActivationDate": "0820",
        "ExpirationDate": "1217",
        "Exponent": 3,
        "Modulus": "0xA6DA428387A502D7DDFB7A74D3F412BE762627197B25435B7A81716A700157DDD06F7CC99D6CA28C2470527E2C03616B9C59217357C2674F583B3BA5C7DCF2838692D023E3562420B4615C439CA97C44DC9A249CFCE7B3BFB22F68228C3AF13329AA4A613CF8DD853502373D62E49AB256D2BC17120E54AEDCED6D96A4287ACC5C04677D4A5A320DB8BEE2F775E5FEC5",
        "Checksum": "0x381A035DA58B482EE2AF75F4C3F2CA469BA4AA6C",
        "IsRevoked": false,
        "CertificateSerialNumber": "0x000001"
      },
      {
        "RegisteredApplicationProviderIndicator": "0xA000000004",
        "PublicKeyIndex": "0x5",
        "HashAlgorithmIndicator": 1,
        "PublicKeyAlgorithmIndicator": 1,
        "ActivationDate": "0820",
        "ExpirationDate": "1224",
        "Exponent": 3,
        "Modulus": "0xB8048ABC30C90D976336543E3FD7091C8FE4800DF820ED55E7E94813ED00555B573FECA3D84AF6131A651D66CFF4284FB13B635EDD0EE40176D8BF04B7FD1C7BACF9AC7327DFAA8AA72D10DB3B8E70B2DDD811CB4196525EA386ACC33C0D9D4575916469C4E4F53E8E1C912CC618CB22DDE7C3568E90022E6BBA770202E4522A2DD623D180E215BD1D1507FE3DC90CA310D27B3EFCCD8F83DE3052CAD1E48938C68D095AAC91B5F37E28BB49EC7ED597",
        "Checksum": "0xEBFA0D5D06D8CE702DA3EAE890701D45E274C845",
        "IsRevoked": false,
        "CertificateSerialNumber": "0x000001"
      },
      {
        "RegisteredApplicationProviderIndicator": "0xA000000004",
        "PublicKeyIndex": "0x6",
        "HashAlgorithmIndicator": 1,
        "PublicKeyAlgorithmIndicator": 1,
        "ActivationDate": "0820",
        "ExpirationDate": "1228",
        "Exponent": 3,
        "Modulus": "0xCB26FC830B43785B2BCE37C81ED334622F9622F4C89AAE641046B2353433883F307FB7C974162DA72F7A4EC75D9D657336865B8D3023D3D645667625C9A07A6B7A137CF0C64198AE38FC238006FB2603F41F4F3BB9DA1347270F2F5D8C606E420958C5F7D50A71DE30142F70DE468889B5E3A08695B938A50FC980393A9CBCE44AD2D64F630BB33AD3F5F5FD495D31F37818C1D94071342E07F1BEC2194F6035BA5DED3936500EB82DFDA6E8AFB655B1EF3D0D7EBF86B66DD9F29F6B1D324FE8B26CE38AB2013DD13F611E7A594D675C4432350EA244CC34F3873CBA06592987A1D7E852ADC22EF5A2EE28132031E48F74037E3B34AB747F",
        "Checksum": "0xF910A1504D5FFB793D94F3B500765E1ABCAD72D9",
        "IsRevoked": false,
        "CertificateSerialNumber": "0x000001"
      },
      {
        "RegisteredApplicationProviderIndicator": "0xA000000003",
        "PublicKeyIndex": "0x1",
        "HashAlgorithmIndicator": 1,
        "PublicKeyAlgorithmIndicator": 1,
        "ActivationDate": "0820",
        "ExpirationDate": "1209",
        "Exponent": 3,
        "Modulus": "0xC696034213D7D8546984579D1D0F0EA519CFF8DEFFC429354CF3A871A6F7183F1228DA5C7470C055387100CB935A712C4E2864DF5D64BA93FE7E63E71F25B1E5F5298575EBE1C63AA617706917911DC2A75AC28B251C7EF40F2365912490B939BCA2124A30A28F54402C34AECA331AB67E1E79B285DD5771B5D9FF79EA630B75",
        "Checksum": "0xD34A6A776011C7E7CE3AEC5F03AD2F8CFC5503CC",
        "IsRevoked": false,
        "CertificateSerialNumber": "0x000001"
      },
      {
        "RegisteredApplicationProviderIndicator": "0xA000000003",
        "PublicKeyIndex": "0x7",
        "HashAlgorithmIndicator": 1,
        "PublicKeyAlgorithmIndicator": 1,
        "ActivationDate": "0820",
        "ExpirationDate": "1217",
        "Exponent": 3,
        "Modulus": "0xA89F25A56FA6DA258C8CA8B40427D927B4A1EB4D7EA326BBB12F97DED70AE5E4480FC9C5E8A972177110A1CC318D06D2F8F5C4844AC5FA79A4DC470BB11ED635699C17081B90F1B984F12E92C1C529276D8AF8EC7F28492097D8CD5BECEA16FE4088F6CFAB4A1B42328A1B996F9278B0B7E3311CA5EF856C2F888474B83612A82E4E00D0CD4069A6783140433D50725F",
        "Checksum": "0xB4BC56CC4E88324932CBC643D6898F6FE593B172",
        "IsRevoked": false,
        "CertificateSerialNumber": "0x000001"
      },
      {
        "RegisteredApplicationProviderIndicator": "0xA000000003",
        "PublicKeyIndex": "0x8",
        "HashAlgorithmIndicator": 1,
        "PublicKeyAlgorithmIndicator": 1,
        "ActivationDate": "0820",
        "ExpirationDate": "1224",
        "Exponent": 3,
        "Modulus": "0xD9FD6ED75D51D0E30664BD157023EAA1FFA871E4DA65672B863D255E81E137A51DE4F72BCC9E44ACE12127F87E263D3AF9DD9CF35CA4A7B01E907000BA85D24954C2FCA3074825DDD4C0C8F186CB020F683E02F2DEAD3969133F06F7845166ACEB57CA0FC2603445469811D293BFEFBAFAB57631B3DD91E796BF850A25012F1AE38F05AA5C4D6D03B1DC2E568612785938BBC9B3CD3A910C1DA55A5A9218ACE0F7A21287752682F15832A678D6E1ED0B",
        "Checksum": "0x20D213126955DE205ADC2FD2822BD22DE21CF9A8",
        "IsRevoked": false,
        "CertificateSerialNumber": "0x000001"
      },
      {
        "RegisteredApplicationProviderIndicator": "0xA000000003",
        "PublicKeyIndex": "0x9",
        "HashAlgorithmIndicator": 1,
        "PublicKeyAlgorithmIndicator": 1,
        "ActivationDate": "0820",
        "ExpirationDate": "1228",
        "Exponent": 3,
        "Modulus": "0x9D912248DE0A4E39C1A7DDE3F6D2588992C1A4095AFBD1824D1BA74847F2BC4926D2EFD904B4B54954CD189A54C5D1179654F8F9B0D2AB5F0357EB642FEDA95D3912C6576945FAB897E7062CAA44A4AA06B8FE6E3DBA18AF6AE3738E30429EE9BE03427C9D64F695FA8CAB4BFE376853EA34AD1D76BFCAD15908C077FFE6DC5521ECEF5D278A96E26F57359FFAEDA19434B937F1AD999DC5C41EB11935B44C18100E857F431A4A5A6BB65114F174C2D7B59FDF237D6BB1DD0916E644D709DED56481477C75D95CDD68254615F7740EC07F330AC5D67BCD75BF23D28A140826C026DBDE971A37CD3EF9B8DF644AC385010501EFC6509D7A41",
        "Checksum": "0x1FF80A40173F52D7D27E0F26A146A1C8CCB29046",
        "IsRevoked": false,
        "CertificateSerialNumber": "0x000001"
      },
      {
        "RegisteredApplicationProviderIndicator": "0xA000000524",
        "PublicKeyIndex": "0x3",
        "HashAlgorithmIndicator": 1,
        "PublicKeyAlgorithmIndicator": 1,
        "ActivationDate": "0820",
        "ExpirationDate": "1217",
        "Exponent": 3,
        "Modulus": "0xE703A908FFAE3730F82E550869A294C1FF1DA25F2B53D2C8BB18F770DAD505135D03D5EC8EE3926550051C3D4857F6FEDB882C2889E0B25F389F78741F2931A92D45D3A47E62810D3253653AB0AB3570C35DFD08D3167B6DB42ED28F765186F4287CDAF9D9BAD20BCE2C4ECFECDD218E50F1FCC718878882F3934A6FEB502CFCAD615A2B2E279A0868DDA9489DFA9CD9",
        "Checksum": "0x4B93D1E1F57CFA16970501F17D3E06411043F1D5",
        "IsRevoked": false,
        "CertificateSerialNumber": "0x000001"
      },
      {
        "RegisteredApplicationProviderIndicator": "0xA000000524",
        "PublicKeyIndex": "0x4",
        "HashAlgorithmIndicator": 1,
        "PublicKeyAlgorithmIndicator": 1,
        "ActivationDate": "0820",
        "ExpirationDate": "1224",
        "Exponent": 3,
        "Modulus": "0xAC0019624FC0A72270C6885CC0B3C9140C351FCFE6F8145881A27750393453D3265F69E7658132D8D253EDF8991E2BA32B782D39ADE1FF1FC8F211F5DF51A0007C761AD9882587BD6A36AECD3ABBF944307AC97A2D905FAB489C3E1CCD76DE9EB93ECFAB2BB84F34E770119E356DC6372D8685DA8EB92FCAC7B53C0167100E4CDFB9830D1C45E787E44C9F6A42EC131A6A4CD66BBE4F93CA91FDF157C7B22FC7221A6348F0EDA6151302A80EF77D6CA5",
        "Checksum": "0x6F843CE765B9144CE1A6BFEA46BC37B65081CE7F",
        "IsRevoked": false,
        "CertificateSerialNumber": "0x000001"
      },
      {
        "RegisteredApplicationProviderIndicator": "0xA000000524",
        "PublicKeyIndex": "0x5",
        "HashAlgorithmIndicator": 1,
        "PublicKeyAlgorithmIndicator": 1,
        "ActivationDate": "0820",
        "ExpirationDate": "1224",
        "Exponent": 3,
        "Modulus": "0xC04E80180369898AAEF6EE7741EDED25239D765301614B5B41A008CA3009358D626D828BC5F1B1E04A2DC1367101266905D262003BE747FD231C9B0011F2F2B21BA8E4C0F4CA5E93ED9DBB2E92ABC450576A4EB59AD00DCA59C8BF3230E4B19D43452871C6215D837663310DF43CAEA1B9B08C1F500AF1B550F62E18D70EEE9E9475321BCD1799AB193E0BC849DACE892A0E6A1F42FE0786DB30345AE1A0E7E4C4B71640E03BFD2832C491A7D83F3B4EF4D388CDDBB748C2FD1D9D4A9BF52FC856CBA088D4B274846002C23CDA722C5CFF3B1F8218A1843B0426474BDC92F2F5E31FBF321CC17480AD069DF55381F2E601D5CBA7B871253F",
        "Checksum": "0x7081DF2A0C36360F24C122C574F0AD2E57893DD2",
        "IsRevoked": false,
        "CertificateSerialNumber": "0x000001"
      },
      {
        "RegisteredApplicationProviderIndicator": "0xA000000524",
        "PublicKeyIndex": "0x6",
        "HashAlgorithmIndicator": 1,
        "PublicKeyAlgorithmIndicator": 1,
        "ActivationDate": "0820",
        "ExpirationDate": "1224",
        "Exponent": 3,
        "Modulus": "0x9D8A75B36BCBDF250B87615A46F6EA35DE35226EEAB7B473D7DC0A28B5DF075C83B2775F23337E6CEE36CCFE3A6568C9C822D6DE81299565A829348E03D479B631BB18A2429A8590C597F446A3CEA3BE2E822106F43DFBB981EC0F1121919CB35F85DBA3355C5E7FF35F2B221FD65EDBEA41F23A7A109FBBC4A774A756D89B593B199E1E9DA9A99217D4BF31F67CDA8C4E1B81FA2A377C83B5D1CD6AF1F1880448CFF48D3A4ADBBC7FBD730061508A6EA8FDFC5BD66A2E94E33B83F81E0E56CF1C9473E4426EE435F9E80136760D8F4AD946805B03A67C55361582F5AD8F40404392FA4CB4F5C2BAF6E26857A1D60941E3D055ACD9AC0BEF",
        "Checksum": "0xE98F4134E1949A9A054E4679AC9A7EC83969E209",
        "IsRevoked": false,
        "CertificateSerialNumber": "0x000001"
      },
      {
        "RegisteredApplicationProviderIndicator": "0xA000000042",
        "PublicKeyIndex": "0x4",
        "HashAlgorithmIndicator": 1,
        "PublicKeyAlgorithmIndicator": 1,
        "ActivationDate": "0820",
        "ExpirationDate": "1217",
        "Exponent": 3,
        "Modulus": "0xD020CF4811D0F07E45C78AAC85DA5D9C5F499E70A40D9F7F51954B8F888DFE811339984FF77BAC996792C73B50BF220EA86B016DA7F33B177B3765AB9469A785646311D649F0C468D29AA23F60D191EDFFD60D7A51834306453A1BC839CB858E91FB10C8E9BB7491FB036A0D3CE84A42EA045A294B82E63C9A6EAE360F35BC0B2438389D8D780F4C788364D2D3034931",
        "Checksum": "0x95482A832B5B980A9F9C78BE810E149AC9425F47",
        "IsRevoked": false,
        "CertificateSerialNumber": "0x000001"
      },
      {
        "RegisteredApplicationProviderIndicator": "0xA000000042",
        "PublicKeyIndex": "0x6",
        "HashAlgorithmIndicator": 1,
        "PublicKeyAlgorithmIndicator": 1,
        "ActivationDate": "0820",
        "ExpirationDate": "1217",
        "Exponent": 3,
        "Modulus": "0xB54B1057A9FEFDE4AB0B0AF8AFBF9BF0DECE975AE949391ADDE454D7455CE377BF3E5F5A4510C74347F01D029490B1E834364209CF4E89E23A242135D1E61BF1AF5A1E5C770A4637DEE81661775BF12BB8F0337325537AACFE73507EA0A3CE4C309BEF404ED45C6927F84FF25101A295224B39FC8983954AB291BFF6B45E12BECDF2AE513B14BDD40938545C20F2A3D9",
        "Checksum": "0xEF6EFF2FB8909A9B2EDF8ABB3E2AF1CC38B3BD19",
        "IsRevoked": false,
        "CertificateSerialNumber": "0x000001"
      },
      {
        "RegisteredApplicationProviderIndicator": "0xA000000042",
        "PublicKeyIndex": "0x7",
        "HashAlgorithmIndicator": 1,
        "PublicKeyAlgorithmIndicator": 1,
        "ActivationDate": "0820",
        "ExpirationDate": "1221",
        "Exponent": 3,
        "Modulus": "0xBA6D5B9CD83579E91864B6B66B274C0A6AB298BCE2842CFA53B070356EAD3E7CB5888FEFFEC1B657A9BE0A5AF576A8D98C88A2E3C98BB0DEAEE4EADDB2E90066A703B549EC048054E82CBA7EDB14BC8C1A5A07BE03EED8F13515806FA0F1B9FAE96DE4142ABD4ABBC8B7CCF7DEFBCAB39C5A12B1FE68C4BDED29F3D3F06BF6E58BA8CB47483F92BAC76971EF895A57FC3E6F46BF43F9F1BCAE4F42FF00B1B45F6CC47F4AFCE844A8E7CF35A499FA54ED",
        "Checksum": "0x1423BF39A1B0720F534F375423F7AE8D7DD2F46E",
        "IsRevoked": false,
        "CertificateSerialNumber": "0x000001"
      },
      {
        "RegisteredApplicationProviderIndicator": "0xA000000042",
        "PublicKeyIndex": "0x8",
        "HashAlgorithmIndicator": 1,
        "PublicKeyAlgorithmIndicator": 1,
        "ActivationDate": "0820",
        "ExpirationDate": "1221",
        "Exponent": 3,
        "Modulus": "0xD3E3463D40039DF15FA530D4367B3B558C9B18B34C972263321469803421E81B75DD9CA5E3578DC41FB24D0F4B85EF6E9DBFAEAA47E2533542B2EC397A2818774F2B9B319C18CEEA3A8C66870E31382F582D2C66164252DD43129208B6F399554C584E43D3F984383CB86691B5D81C9CA9089A289A08B22CEBCF9C0E7BB2458FC057D9C56D0B9B4E636B64A359C07D43F8305B5027851FFCA43788A5A387FED750DBAED61C78524DDE2E36F090C52913BF909DF1A2FD3C178C8D2E3007CA2CA67CEA7CF02ACF8A228DBEA7589B2CC19305B3C0A64EFD47242A6FD958A381EFAEC191B790A9ABDB043D1AB1BDB8AAB66D0FE0DC82A0738FAB",
        "Checksum": "0x8519DA94E938A5352AE07990D15AD40DBB9A8F1C",
        "IsRevoked": false,
        "CertificateSerialNumber": "0x000001"
      },
      {
        "RegisteredApplicationProviderIndicator": "0xA000000042",
        "PublicKeyIndex": "0x85",
        "HashAlgorithmIndicator": 1,
        "PublicKeyAlgorithmIndicator": 1,
        "ActivationDate": "0820",
        "ExpirationDate": "1218",
        "Exponent": 3,
        "Modulus": "0xD5BD27FFD68F05C916C4A113B82965F06BB9BD84D1D04669BAAF2D7040D072FC4A16D167A5D99DB5CA4466F556B46174EF8E65D6CA779BB8557F3E5AD861A725717F7A7D70F41DA53F6A574EDA648762C8637A8602BDA378DDD6DFACDDB1563662B78F1E25F7FC8164081E293D5CBF3F57187033A968AE173BE7D78A46CB70EA68FB65DD5019CD400421CBB703702475",
        "Checksum": "0xE882F47B8EF925BEDDF32C20555827DA7FDD7570",
        "IsRevoked": false,
        "CertificateSerialNumber": "0x000001"
      },
      {
        "RegisteredApplicationProviderIndicator": "0xA000000042",
        "PublicKeyIndex": "0x86",
        "HashAlgorithmIndicator": 1,
        "PublicKeyAlgorithmIndicator": 1,
        "ActivationDate": "0820",
        "ExpirationDate": "1218",
        "Exponent": 3,
        "Modulus": "0xD7686F54E4C65DFC162B455D612D918739059BA2445B79A1BD070A448CE062BD0C6E7E5683223490C66AB4B808A4D3A59E276D8B779925752FCE140BA136C0E05C0BDBAE0A9F751B9340BA88603967F43D40A04CFD652503B78234D188F6B21D5A3AE99BB84B2E50235EF9D7ED7A70A117806778E9F0D1B3DADC1CE9B25C2DDE07B3B6E1DE487E0F7E9FFEDDD4D15255CEC453631EF47E14B498A353844802A4A25A62B9918E9A12A00BF887AAD4799F",
        "Checksum": "0x96A690811AA2196E3D1090CE0149AA2935C04FE2",
        "IsRevoked": false,
        "CertificateSerialNumber": "0x000001"
      },
      {
        "RegisteredApplicationProviderIndicator": "0xA000000461",
        "PublicKeyIndex": "0xA2",
        "HashAlgorithmIndicator": 1,
        "PublicKeyAlgorithmIndicator": 1,
        "ActivationDate": "0820",
        "ExpirationDate": "1224",
        "Exponent": 3,
        "Modulus": "0xBF323DADF0D07C8B4A1CE837A2919B64BA821A4DDD15709690F940B97E9B78DECC37C806771A7CD70B2625C69618C80F05A6652B87E0C4B69F9C7B2CD5C24A8AB756BFF2BB11C3C177ABC82224D62DB1017EABC48564B177E06FE00C48C1280CCCAC4016566F9B45CB34FF91A25D056DFC71969E150C498F02F78ECB82DD3004FA3734A6F5077AECCC6C6060EACE0126D0ECAE5F404DE9B8ACB30EB604CA055ED0BB790672F4C938CC92231E4A48E55B",
        "Checksum": "0x6CBF00F2579E999CEAD14FC18C57B795257C6C9C",
        "IsRevoked": false,
        "CertificateSerialNumber": "0x000001"
      }
    ]
  }
}