<?xml version="1.0" encoding="utf-8"?>
<resources xmlns:tools="http://schemas.android.com/tools">
  <color name="accent_color">#00C3D9</color>
  <color name="accent_color_with_opacity">#4000C3D9</color>
  <color name="primary_color">@color/white</color>
  <color name="secondary_color">#213848</color>
  <color name="third_color">#F4F6F9</color>
  <color name="secondary_dark_color">#192E3A</color>
  <color name="primary_text_color">#213848</color>
  <color name="hint_text_color">#B0B0B9</color>
  <color name="secondary_text_color">#D1DBE8</color>
  <color name="separator_color">#F4F6F9</color>
  <color name="negative_color">#DF3868</color>
  <color name="positive_color">#00D994</color>
  <color name="greyed_out">#33AAAFB4</color>
  <color name="bright_gray">#E8EDF3</color>
  <color name="chart_primary_color">#00C3D9</color>
  <color name="chart_secondary_color">#6239BF</color>
  <color name="black">#FF000000</color>
  <color name="white">#FFFFFFFF</color>
  <color name="transparent_white">#80FFFFFF</color>
  <color name="transparent">#00000000</color>

  <color name="mtrl_textinput_default_box_stroke_color" tools:override="true">#00C3D9</color>
</resources>